menglingtool_spiders/__init__.py
menglingtool_spiders/appium.py
menglingtool_spiders/proxy.py
menglingtool_spiders/pyppeteer.py
menglingtool_spiders/selenium.py
menglingtool_spiders/__pyppeteer__/action.py
menglingtool_spiders/__pyppeteer__/base.py
menglingtool_spiders/__pyppeteer__/request.py
menglingtool_spiders/__selenium__/get.py
menglingtool_spiders/__selenium__/init.py
menglingtool_spiders/__selenium__/open.py
menglingtool_spiders/__selenium__/operation.py
menglingtool_spiders/__selenium__/stealth_min_js.py
menglingtool_spiders/__selenium__/wait.py
menglingtool_spiders/functions/action.py
menglingtool_spiders/functions/args_get.py
menglingtool_spiders/functions/cookie.py
menglingtool_spiders/functions/download.py
menglingtool_spiders/functions/make.py
menglingtool_spiders/functions/parsing_tool.py
menglingtool_spiders/spiders/__superclass__.py
menglingtool_spiders/spiders/httpSession.py
menglingtool_spiders/spiders/httplib2.py
menglingtool_spiders/spiders/httpx.py
menglingtool_spiders/spiders/requests.py
menglingtool_spiders/spiders/session.py
menglingtool_spiders/spiders/spider_all.py
menglingtool_spiders-1.1.1.dist-info/METADATA
menglingtool_spiders-1.1.1.dist-info/WHEEL
menglingtool_spiders-1.1.1.dist-info/top_level.txt
menglingtool_spiders-1.1.1.dist-info/RECORD
