Metadata-Version: 2.1
Name: menglingtool-spiders
Version: 1.1.1
Summary: 工业化! yyds
Home-page: https://www.python.org
Author: mengling
Author-email: 1321443305@qq.com
Requires-Python: >3.6
Requires-Dist: requests
